dictionary/__init__.py
dictionary/dictionary.py
melih_diksu_dictionary-2.0.0.dist-info/METADATA
melih_diksu_dictionary-2.0.0.dist-info/WHEEL
melih_diksu_dictionary-2.0.0.dist-info/top_level.txt
melih_diksu_dictionary-2.0.0.dist-info/RECORD
